[
    {
        "name": "701. Insert into a Binary Search Tree",
        "url": "https://leetcode.com/problems/insert-into-a-binary-search-tree",
        "difficulty": "Medium"
    },
    {
        "name": "702. Search in a Sorted Array of Unknown Size",
        "url": "https://leetcode.com/problems/search-in-a-sorted-array-of-unknown-size",
        "difficulty": "Medium"
    },
    {
        "name": "703. Kth Largest Element in a Stream",
        "url": "https://leetcode.com/problems/kth-largest-element-in-a-stream",
        "difficulty": "Easy"
    },
    {
        "name": "704. Binary Search",
        "url": "https://leetcode.com/problems/binary-search",
        "difficulty": "Easy"
    },
    {
        "name": "705. Design HashSet",
        "url": "https://leetcode.com/problems/design-hashset",
        "difficulty": "Easy"
    },
    {
        "name": "706. Design HashMap",
        "url": "https://leetcode.com/problems/design-hashmap",
        "difficulty": "Easy"
    },
    {
        "name": "707. Design Linked List",
        "url": "https://leetcode.com/problems/design-linked-list",
        "difficulty": "Medium"
    },
    {
        "name": "708. Insert into a Sorted Circular Linked List",
        "url": "https://leetcode.com/problems/insert-into-a-sorted-circular-linked-list",
        "difficulty": "Medium"
    },
    {
        "name": "709. To Lower Case",
        "url": "https://leetcode.com/problems/to-lower-case",
        "difficulty": "Easy"
    },
    {
        "name": "710. Random Pick with Blacklist",
        "url": "https://leetcode.com/problems/random-pick-with-blacklist",
        "difficulty": "Hard"
    },
    {
        "name": "711. Number of Distinct Islands II",
        "url": "https://leetcode.com/problems/number-of-distinct-islands-ii",
        "difficulty": "Hard"
    },
    {
        "name": "712. Minimum ASCII Delete Sum for Two Strings",
        "url": "https://leetcode.com/problems/minimum-ascii-delete-sum-for-two-strings",
        "difficulty": "Medium"
    },
    {
        "name": "713. Subarray Product Less Than K",
        "url": "https://leetcode.com/problems/subarray-product-less-than-k",
        "difficulty": "Medium"
    },
    {
        "name": "714. Best Time to Buy and Sell Stock with Transaction Fee",
        "url": "https://leetcode.com/problems/best-time-to-buy-and-sell-stock-with-transaction-fee",
        "difficulty": "Medium"
    },
    {
        "name": "715. Range Module",
        "url": "https://leetcode.com/problems/range-module",
        "difficulty": "Hard"
    },
    {
        "name": "716. Max Stack",
        "url": "https://leetcode.com/problems/max-stack",
        "difficulty": "Hard"
    },
    {
        "name": "717. 1-bit and 2-bit Characters",
        "url": "https://leetcode.com/problems/1-bit-and-2-bit-characters",
        "difficulty": "Easy"
    },
    {
        "name": "718. Maximum Length of Repeated Subarray",
        "url": "https://leetcode.com/problems/maximum-length-of-repeated-subarray",
        "difficulty": "Medium"
    },
    {
        "name": "719. Find K-th Smallest Pair Distance",
        "url": "https://leetcode.com/problems/find-k-th-smallest-pair-distance",
        "difficulty": "Hard"
    },
    {
        "name": "720. Longest Word in Dictionary",
        "url": "https://leetcode.com/problems/longest-word-in-dictionary",
        "difficulty": "Medium"
    },
    {
        "name": "721. Accounts Merge",
        "url": "https://leetcode.com/problems/accounts-merge",
        "difficulty": "Medium"
    },
    {
        "name": "722. Remove Comments",
        "url": "https://leetcode.com/problems/remove-comments",
        "difficulty": "Medium"
    },
    {
        "name": "723. Candy Crush",
        "url": "https://leetcode.com/problems/candy-crush",
        "difficulty": "Medium"
    },
    {
        "name": "724. Find Pivot Index",
        "url": "https://leetcode.com/problems/find-pivot-index",
        "difficulty": "Easy"
    },
    {
        "name": "725. Split Linked List in Parts",
        "url": "https://leetcode.com/problems/split-linked-list-in-parts",
        "difficulty": "Medium"
    },
    {
        "name": "726. Number of Atoms",
        "url": "https://leetcode.com/problems/number-of-atoms",
        "difficulty": "Hard"
    },
    {
        "name": "727. Minimum Window Subsequence",
        "url": "https://leetcode.com/problems/minimum-window-subsequence",
        "difficulty": "Hard"
    },
    {
        "name": "728. Self Dividing Numbers",
        "url": "https://leetcode.com/problems/self-dividing-numbers",
        "difficulty": "Easy"
    },
    {
        "name": "729. My Calendar I",
        "url": "https://leetcode.com/problems/my-calendar-i",
        "difficulty": "Medium"
    },
    {
        "name": "730. Count Different Palindromic Subsequences",
        "url": "https://leetcode.com/problems/count-different-palindromic-subsequences",
        "difficulty": "Hard"
    },
    {
        "name": "731. My Calendar II",
        "url": "https://leetcode.com/problems/my-calendar-ii",
        "difficulty": "Medium"
    },
    {
        "name": "732. My Calendar III",
        "url": "https://leetcode.com/problems/my-calendar-iii",
        "difficulty": "Hard"
    },
    {
        "name": "733. Flood Fill",
        "url": "https://leetcode.com/problems/flood-fill",
        "difficulty": "Easy"
    },
    {
        "name": "734. Sentence Similarity",
        "url": "https://leetcode.com/problems/sentence-similarity",
        "difficulty": "Easy"
    },
    {
        "name": "735. Asteroid Collision",
        "url": "https://leetcode.com/problems/asteroid-collision",
        "difficulty": "Medium"
    },
    {
        "name": "736. Parse Lisp Expression",
        "url": "https://leetcode.com/problems/parse-lisp-expression",
        "difficulty": "Hard"
    },
    {
        "name": "737. Sentence Similarity II",
        "url": "https://leetcode.com/problems/sentence-similarity-ii",
        "difficulty": "Medium"
    },
    {
        "name": "738. Monotone Increasing Digits",
        "url": "https://leetcode.com/problems/monotone-increasing-digits",
        "difficulty": "Medium"
    },
    {
        "name": "739. Daily Temperatures",
        "url": "https://leetcode.com/problems/daily-temperatures",
        "difficulty": "Medium"
    },
    {
        "name": "740. Delete and Earn",
        "url": "https://leetcode.com/problems/delete-and-earn",
        "difficulty": "Medium"
    },
    {
        "name": "741. Cherry Pickup",
        "url": "https://leetcode.com/problems/cherry-pickup",
        "difficulty": "Hard"
    },
    {
        "name": "742. Closest Leaf in a Binary Tree",
        "url": "https://leetcode.com/problems/closest-leaf-in-a-binary-tree",
        "difficulty": "Medium"
    },
    {
        "name": "743. Network Delay Time",
        "url": "https://leetcode.com/problems/network-delay-time",
        "difficulty": "Medium"
    },
    {
        "name": "744. Find Smallest Letter Greater Than Target",
        "url": "https://leetcode.com/problems/find-smallest-letter-greater-than-target",
        "difficulty": "Easy"
    },
    {
        "name": "745. Prefix and Suffix Search",
        "url": "https://leetcode.com/problems/prefix-and-suffix-search",
        "difficulty": "Hard"
    },
    {
        "name": "746. Min Cost Climbing Stairs",
        "url": "https://leetcode.com/problems/min-cost-climbing-stairs",
        "difficulty": "Easy"
    },
    {
        "name": "747. Largest Number At Least Twice of Others",
        "url": "https://leetcode.com/problems/largest-number-at-least-twice-of-others",
        "difficulty": "Easy"
    },
    {
        "name": "748. Shortest Completing Word",
        "url": "https://leetcode.com/problems/shortest-completing-word",
        "difficulty": "Easy"
    },
    {
        "name": "749. Contain Virus",
        "url": "https://leetcode.com/problems/contain-virus",
        "difficulty": "Hard"
    },
    {
        "name": "750. Number Of Corner Rectangles",
        "url": "https://leetcode.com/problems/number-of-corner-rectangles",
        "difficulty": "Medium"
    }
]